naver_api/__init__.py
naver_api/naver_search.py
naver_api-0.1.dist-info/METADATA
naver_api-0.1.dist-info/WHEEL
naver_api-0.1.dist-info/top_level.txt
naver_api-0.1.dist-info/RECORD
