Metadata-Version: 2.1
Name: naver-api
Version: 0.1
Summary: The naver api joke in the world
Home-page: https://github.com/harry81/naver_api
Author: Hyunmin Choi
Author-email: pointer81@gmail.com
License: MIT
Platform: UNKNOWN
Requires-Dist: bs4
